cs2cpp/CSharpToCpp.py
cs2cpp/__init__.py
cs2cpp-0.1.1.dist-info/METADATA
cs2cpp-0.1.1.dist-info/WHEEL
cs2cpp-0.1.1.dist-info/top_level.txt
cs2cpp-0.1.1.dist-info/RECORD
